{
    "@context": "http://iiif.io/api/presentation/2/context.json",
    "@id": "https://readux.io/iiif/v2/tsnhf/list/tsnhf_00000036.tif",
    "@type": "sc:AnnotationList",
    "resources": [
        {
            "@context": "http://iiif.io/api/presentation/2/context.json",
            "@id": "22410a9e-a04c-4d73-a604-1116ec57673d",
            "@type": "oa:Annotation",
            "motivation": "sc:painting",
            "annotatedBy": {
                "name": "OCR"
            },
            "resource": {
                "@type": "cnt:ContentAsText",
                "format": "text/html",
                "chars": "<span id='22410a9e-a04c-4d73-a604-1116ec57673d' data-letter-spacing='0.08514492753623187'>FLIGHT</span>",
                "language": "en"
            },
            "on": {
                "full": "https://readux.io/iiif/v2/tsnhf/canvas/tsnhf_00000036.tif",
                "@type": "oa:SpecificResource",
                "within": {
                    "@id": "https://readux.io/iiif/v2/tsnhf/manifest",
                    "@type": "sc:Manifest"
                },
                "selector": {
                    "@type": "oa:FragmentSelector",
                    "value": "xywh=2431,595,529,138",
                    "item": {
                        "@type": "oa:FragmentSelector"
                    }
                }
            },
            "stylesheet": {
                "type": "CssStylesheet",
                "value": ".anno-22410a9e-a04c-4d73-a604-1116ec57673d: { height: 138px; width: 529px; font-size: 86.25px; }"
            }
        },
        {
            "@context": "http://iiif.io/api/presentation/2/context.json",
            "@id": "345db36d-3fae-43b0-a65a-3178adbe9f28",
            "@type": "oa:Annotation",
            "motivation": "sc:painting",
            "annotatedBy": {
                "name": "OCR"
            },
            "resource": {
                "@type": "cnt:ContentAsText",
                "format": "text/html",
                "chars": "<span id='345db36d-3fae-43b0-a65a-3178adbe9f28' data-letter-spacing='0.13561007957559681'>PLAN</span>",
                "language": "en"
            },
            "on": {
                "full": "https://readux.io/iiif/v2/tsnhf/canvas/tsnhf_00000036.tif",
                "@type": "oa:SpecificResource",
                "within": {
                    "@id": "https://readux.io/iiif/v2/tsnhf/manifest",
                    "@type": "sc:Manifest"
                },
                "selector": {
                    "@type": "oa:FragmentSelector",
                    "value": "xywh=3030,595,377,138",
                    "item": {
                        "@type": "oa:FragmentSelector"
                    }
                }
            },
            "stylesheet": {
                "type": "CssStylesheet",
                "value": ".anno-345db36d-3fae-43b0-a65a-3178adbe9f28: { height: 138px; width: 377px; font-size: 86.25px; }"
            }
        },
        {
            "@context": "http://iiif.io/api/presentation/2/context.json",
            "@id": "ee2ae5d6-39e0-472f-8cae-6dd5f33bc783",
            "@type": "oa:Annotation",
            "motivation": "sc:painting",
            "annotatedBy": {
                "name": "OCR"
            },
            "resource": {
                "@type": "cnt:ContentAsText",
                "format": "text/html",
                "chars": "<span id='ee2ae5d6-39e0-472f-8cae-6dd5f33bc783' data-letter-spacing='0.15544871794871795'>MCC</span>",
                "language": "en"
            },
            "on": {
                "full": "https://readux.io/iiif/v2/tsnhf/canvas/tsnhf_00000036.tif",
                "@type": "oa:SpecificResource",
                "within": {
                    "@id": "https://readux.io/iiif/v2/tsnhf/manifest",
                    "@type": "sc:Manifest"
                },
                "selector": {
                    "@type": "oa:FragmentSelector",
                    "value": "xywh=2844,1742,130,74",
                    "item": {
                        "@type": "oa:FragmentSelector"
                    }
                }
            },
            "stylesheet": {
                "type": "CssStylesheet",
                "value": ".anno-ee2ae5d6-39e0-472f-8cae-6dd5f33bc783: { height: 74px; width: 130px; font-size: 46.25px; }"
            }
        },
        {
            "@context": "http://iiif.io/api/presentation/2/context.json",
            "@id": "48a5ef1e-8342-49dd-9178-9c3869200a32",
            "@type": "oa:Annotation",
            "motivation": "sc:painting",
            "annotatedBy": {
                "name": "OCR"
            },
            "resource": {
                "@type": "cnt:ContentAsText",
                "format": "text/html",
                "chars": "<span id='48a5ef1e-8342-49dd-9178-9c3869200a32' data-letter-spacing='-0.16776315789473684'>-</span>",
                "language": "en"
            },
            "on": {
                "full": "https://readux.io/iiif/v2/tsnhf/canvas/tsnhf_00000036.tif",
                "@type": "oa:SpecificResource",
                "within": {
                    "@id": "https://readux.io/iiif/v2/tsnhf/manifest",
                    "@type": "sc:Manifest"
                },
                "selector": {
                    "@type": "oa:FragmentSelector",
                    "value": "xywh=2998,1745,19,71",
                    "item": {
                        "@type": "oa:FragmentSelector"
                    }
                }
            },
            "stylesheet": {
                "type": "CssStylesheet",
                "value": ".anno-48a5ef1e-8342-49dd-9178-9c3869200a32: { height: 71px; width: 19px; font-size: 44.375px; }"
            }
        },
        {
            "@context": "http://iiif.io/api/presentation/2/context.json",
            "@id": "53d02ea9-58c2-49e0-9943-8a90b28c7d88",
            "@type": "oa:Annotation",
            "motivation": "sc:painting",
            "annotatedBy": {
                "name": "OCR"
            },
            "resource": {
                "@type": "cnt:ContentAsText",
                "format": "text/html",
                "chars": "<span id='53d02ea9-58c2-49e0-9943-8a90b28c7d88' data-letter-spacing='-0.16776315789473684'>2</span>",
                "language": "en"
            },
            "on": {
                "full": "https://readux.io/iiif/v2/tsnhf/canvas/tsnhf_00000036.tif",
                "@type": "oa:SpecificResource",
                "within": {
                    "@id": "https://readux.io/iiif/v2/tsnhf/manifest",
                    "@type": "sc:Manifest"
                },
                "selector": {
                    "@type": "oa:FragmentSelector",
                    "value": "xywh=3048,1746,19,71",
                    "item": {
                        "@type": "oa:FragmentSelector"
                    }
                }
            },
            "stylesheet": {
                "type": "CssStylesheet",
                "value": ".anno-53d02ea9-58c2-49e0-9943-8a90b28c7d88: { height: 71px; width: 19px; font-size: 44.375px; }"
            }
        },
        {
            "@context": "http://iiif.io/api/presentation/2/context.json",
            "@id": "ebf25ebf-3d17-4303-83f6-753d6cb5abe7",
            "@type": "oa:Annotation",
            "motivation": "sc:painting",
            "annotatedBy": {
                "name": "OCR"
            },
            "resource": {
                "@type": "cnt:ContentAsText",
                "format": "text/html",
                "chars": "<span id='ebf25ebf-3d17-4303-83f6-753d6cb5abe7' data-letter-spacing='0.11842105263157894'>BURN</span>",
                "language": "en"
            },
            "on": {
                "full": "https://readux.io/iiif/v2/tsnhf/canvas/tsnhf_00000036.tif",
                "@type": "oa:SpecificResource",
                "within": {
                    "@id": "https://readux.io/iiif/v2/tsnhf/manifest",
                    "@type": "sc:Manifest"
                },
                "selector": {
                    "@type": "oa:FragmentSelector",
                    "value": "xywh=2741,1837,171,72",
                    "item": {
                        "@type": "oa:FragmentSelector"
                    }
                }
            },
            "stylesheet": {
                "type": "CssStylesheet",
                "value": ".anno-ebf25ebf-3d17-4303-83f6-753d6cb5abe7: { height: 72px; width: 171px; font-size: 45.0px; }"
            }
        },
        {
            "@context": "http://iiif.io/api/presentation/2/context.json",
            "@id": "55f350b1-7895-42a2-97fd-bf0b43d2f700",
            "@type": "oa:Annotation",
            "motivation": "sc:painting",
            "annotatedBy": {
                "name": "OCR"
            },
            "resource": {
                "@type": "cnt:ContentAsText",
                "format": "text/html",
                "chars": "<span id='55f350b1-7895-42a2-97fd-bf0b43d2f700' data-letter-spacing='0.09332932692307692'>TABLE</span>",
                "language": "en"
            },
            "on": {
                "full": "https://readux.io/iiif/v2/tsnhf/canvas/tsnhf_00000036.tif",
                "@type": "oa:SpecificResource",
                "within": {
                    "@id": "https://readux.io/iiif/v2/tsnhf/manifest",
                    "@type": "sc:Manifest"
                },
                "selector": {
                    "@type": "oa:FragmentSelector",
                    "value": "xywh=2981,1835,208,71",
                    "item": {
                        "@type": "oa:FragmentSelector"
                    }
                }
            },
            "stylesheet": {
                "type": "CssStylesheet",
                "value": ".anno-55f350b1-7895-42a2-97fd-bf0b43d2f700: { height: 71px; width: 208px; font-size: 44.375px; }"
            }
        },
        {
            "@context": "http://iiif.io/api/presentation/2/context.json",
            "@id": "a51ad7d6-be74-463f-8e64-926ae633ac2e",
            "@type": "oa:Annotation",
            "motivation": "sc:painting",
            "annotatedBy": {
                "name": "OCR"
            },
            "resource": {
                "@type": "cnt:ContentAsText",
                "format": "text/html",
                "chars": "<span id='a51ad7d6-be74-463f-8e64-926ae633ac2e' data-letter-spacing='-0.08695652173913043'>P</span>",
                "language": "en"
            },
            "on": {
                "full": "https://readux.io/iiif/v2/tsnhf/canvas/tsnhf_00000036.tif",
                "@type": "oa:SpecificResource",
                "within": {
                    "@id": "https://readux.io/iiif/v2/tsnhf/manifest",
                    "@type": "sc:Manifest"
                },
                "selector": {
                    "@type": "oa:FragmentSelector",
                    "value": "xywh=1505,2093,23,80",
                    "item": {
                        "@type": "oa:FragmentSelector"
                    }
                }
            },
            "stylesheet": {
                "type": "CssStylesheet",
                "value": ".anno-a51ad7d6-be74-463f-8e64-926ae633ac2e: { height: 80px; width: 23px; font-size: 50.0px; }"
            }
        },
        {
            "@context": "http://iiif.io/api/presentation/2/context.json",
            "@id": "58489180-790d-4703-b20b-485e0b722869",
            "@type": "oa:Annotation",
            "motivation": "sc:painting",
            "annotatedBy": {
                "name": "OCR"
            },
            "resource": {
                "@type": "cnt:ContentAsText",
                "format": "text/html",
                "chars": "<span id='58489180-790d-4703-b20b-485e0b722869' data-letter-spacing='0.16638513513513514'>OR</span>",
                "language": "en"
            },
            "on": {
                "full": "https://readux.io/iiif/v2/tsnhf/canvas/tsnhf_00000036.tif",
                "@type": "oa:SpecificResource",
                "within": {
                    "@id": "https://readux.io/iiif/v2/tsnhf/manifest",
                    "@type": "sc:Manifest"
                },
                "selector": {
                    "@type": "oa:FragmentSelector",
                    "value": "xywh=1597,2093,74,79",
                    "item": {
                        "@type": "oa:FragmentSelector"
                    }
                }
            },
            "stylesheet": {
                "type": "CssStylesheet",
                "value": ".anno-58489180-790d-4703-b20b-485e0b722869: { height: 79px; width: 74px; font-size: 49.375px; }"
            }
        },
        {
            "@context": "http://iiif.io/api/presentation/2/context.json",
            "@id": "bdf2a172-60f7-44f2-849f-5ab00324c519",
            "@type": "oa:Annotation",
            "motivation": "sc:painting",
            "annotatedBy": {
                "name": "OCR"
            },
            "resource": {
                "@type": "cnt:ContentAsText",
                "format": "text/html",
                "chars": "<span id='bdf2a172-60f7-44f2-849f-5ab00324c519' data-letter-spacing='-0.08695652173913043'>Y</span>",
                "language": "en"
            },
            "on": {
                "full": "https://readux.io/iiif/v2/tsnhf/canvas/tsnhf_00000036.tif",
                "@type": "oa:SpecificResource",
                "within": {
                    "@id": "https://readux.io/iiif/v2/tsnhf/manifest",
                    "@type": "sc:Manifest"
                },
                "selector": {
                    "@type": "oa:FragmentSelector",
                    "value": "xywh=1741,2092,23,80",
                    "item": {
                        "@type": "oa:FragmentSelector"
                    }
                }
            },
            "stylesheet": {
                "type": "CssStylesheet",
                "value": ".anno-bdf2a172-60f7-44f2-849f-5ab00324c519: { height: 80px; width: 23px; font-size: 50.0px; }"
            }
        },
        {
            "@context": "http://iiif.io/api/presentation/2/context.json",
            "@id": "8c24832f-c386-4510-98ff-04bd18d12561",
            "@type": "oa:Annotation",
            "motivation": "sc:painting",
            "annotatedBy": {
                "name": "OCR"
            },
            "resource": {
                "@type": "cnt:ContentAsText",
                "format": "text/html",
                "chars": "<span id='8c24832f-c386-4510-98ff-04bd18d12561' data-letter-spacing='0.08808139534883722'>RATES</span>",
                "language": "en"
            },
            "on": {
                "full": "https://readux.io/iiif/v2/tsnhf/canvas/tsnhf_00000036.tif",
                "@type": "oa:SpecificResource",
                "within": {
                    "@id": "https://readux.io/iiif/v2/tsnhf/manifest",
                    "@type": "sc:Manifest"
                },
                "selector": {
                    "@type": "oa:FragmentSelector",
                    "value": "xywh=1508,2188,215,77",
                    "item": {
                        "@type": "oa:FragmentSelector"
                    }
                }
            },
            "stylesheet": {
                "type": "CssStylesheet",
                "value": ".anno-8c24832f-c386-4510-98ff-04bd18d12561: { height: 77px; width: 215px; font-size: 48.125px; }"
            }
        },
        {
            "@context": "http://iiif.io/api/presentation/2/context.json",
            "@id": "e0eb5796-bbeb-446c-8dc4-9347ad1970f5",
            "@type": "oa:Annotation",
            "motivation": "sc:painting",
            "annotatedBy": {
                "name": "OCR"
            },
            "resource": {
                "@type": "cnt:ContentAsText",
                "format": "text/html",
                "chars": "<span id='e0eb5796-bbeb-446c-8dc4-9347ad1970f5' data-letter-spacing='0.1564922480620155'>ATT</span>",
                "language": "en"
            },
            "on": {
                "full": "https://readux.io/iiif/v2/tsnhf/canvas/tsnhf_00000036.tif",
                "@type": "oa:SpecificResource",
                "within": {
                    "@id": "https://readux.io/iiif/v2/tsnhf/manifest",
                    "@type": "sc:Manifest"
                },
                "selector": {
                    "@type": "oa:FragmentSelector",
                    "value": "xywh=2399,2095,129,73",
                    "item": {
                        "@type": "oa:FragmentSelector"
                    }
                }
            },
            "stylesheet": {
                "type": "CssStylesheet",
                "value": ".anno-e0eb5796-bbeb-446c-8dc4-9347ad1970f5: { height: 73px; width: 129px; font-size: 45.625px; }"
            }
        },
        {
            "@context": "http://iiif.io/api/presentation/2/context.json",
            "@id": "beedafb2-4620-4e94-8e96-a8e79243f6d8",
            "@type": "oa:Annotation",
            "motivation": "sc:painting",
            "annotatedBy": {
                "name": "OCR"
            },
            "resource": {
                "@type": "cnt:ContentAsText",
                "format": "text/html",
                "chars": "<span id='beedafb2-4620-4e94-8e96-a8e79243f6d8' data-letter-spacing='0.046104845446950704'>DEVIATION</span>",
                "language": "en"
            },
            "on": {
                "full": "https://readux.io/iiif/v2/tsnhf/canvas/tsnhf_00000036.tif",
                "@type": "oa:SpecificResource",
                "within": {
                    "@id": "https://readux.io/iiif/v2/tsnhf/manifest",
                    "@type": "sc:Manifest"
                },
                "selector": {
                    "@type": "oa:FragmentSelector",
                    "value": "xywh=2262,2184,399,83",
                    "item": {
                        "@type": "oa:FragmentSelector"
                    }
                }
            },
            "stylesheet": {
                "type": "CssStylesheet",
                "value": ".anno-beedafb2-4620-4e94-8e96-a8e79243f6d8: { height: 83px; width: 399px; font-size: 51.875px; }"
            }
        },
        {
            "@context": "http://iiif.io/api/presentation/2/context.json",
            "@id": "f036a565-5219-464a-b101-0cbd5da9e373",
            "@type": "oa:Annotation",
            "motivation": "sc:painting",
            "annotatedBy": {
                "name": "OCR"
            },
            "resource": {
                "@type": "cnt:ContentAsText",
                "format": "text/html",
                "chars": "<span id='f036a565-5219-464a-b101-0cbd5da9e373' data-letter-spacing='0.05422794117647059'>SHUTDOWN</span>",
                "language": "en"
            },
            "on": {
                "full": "https://readux.io/iiif/v2/tsnhf/canvas/tsnhf_00000036.tif",
                "@type": "oa:SpecificResource",
                "within": {
                    "@id": "https://readux.io/iiif/v2/tsnhf/manifest",
                    "@type": "sc:Manifest"
                },
                "selector": {
                    "@type": "oa:FragmentSelector",
                    "value": "xywh=3226,2093,340,77",
                    "item": {
                        "@type": "oa:FragmentSelector"
                    }
                }
            },
            "stylesheet": {
                "type": "CssStylesheet",
                "value": ".anno-f036a565-5219-464a-b101-0cbd5da9e373: { height: 77px; width: 340px; font-size: 48.125px; }"
            }
        },
        {
            "@context": "http://iiif.io/api/presentation/2/context.json",
            "@id": "6d9e46cf-773b-476d-9cab-7324a6fdfc05",
            "@type": "oa:Annotation",
            "motivation": "sc:painting",
            "annotatedBy": {
                "name": "OCR"
            },
            "resource": {
                "@type": "cnt:ContentAsText",
                "format": "text/html",
                "chars": "<span id='6d9e46cf-773b-476d-9cab-7324a6fdfc05' data-letter-spacing='0.1059131736526946'>TIME</span>",
                "language": "en"
            },
            "on": {
                "full": "https://readux.io/iiif/v2/tsnhf/canvas/tsnhf_00000036.tif",
                "@type": "oa:SpecificResource",
                "within": {
                    "@id": "https://readux.io/iiif/v2/tsnhf/manifest",
                    "@type": "sc:Manifest"
                },
                "selector": {
                    "@type": "oa:FragmentSelector",
                    "value": "xywh=3314,2188,167,77",
                    "item": {
                        "@type": "oa:FragmentSelector"
                    }
                }
            },
            "stylesheet": {
                "type": "CssStylesheet",
                "value": ".anno-6d9e46cf-773b-476d-9cab-7324a6fdfc05: { height: 77px; width: 167px; font-size: 48.125px; }"
            }
        },
        {
            "@context": "http://iiif.io/api/presentation/2/context.json",
            "@id": "f22cf5c4-685a-498d-a9c9-439378b8ee87",
            "@type": "oa:Annotation",
            "motivation": "sc:painting",
            "annotatedBy": {
                "name": "OCR"
            },
            "resource": {
                "@type": "cnt:ContentAsText",
                "format": "text/html",
                "chars": "<span id='f22cf5c4-685a-498d-a9c9-439378b8ee87' data-letter-spacing='0.052376171352074966'>RESIDUALS</span>",
                "language": "en"
            },
            "on": {
                "full": "https://readux.io/iiif/v2/tsnhf/canvas/tsnhf_00000036.tif",
                "@type": "oa:SpecificResource",
                "within": {
                    "@id": "https://readux.io/iiif/v2/tsnhf/manifest",
                    "@type": "sc:Manifest"
                },
                "selector": {
                    "@type": "oa:FragmentSelector",
                    "value": "xywh=4108,2136,415,78",
                    "item": {
                        "@type": "oa:FragmentSelector"
                    }
                }
            },
            "stylesheet": {
                "type": "CssStylesheet",
                "value": ".anno-f22cf5c4-685a-498d-a9c9-439378b8ee87: { height: 78px; width: 415px; font-size: 48.75px; }"
            }
        },
        {
            "@context": "http://iiif.io/api/presentation/2/context.json",
            "@id": "b244a4df-430f-463a-b154-cab2a1c9eeae",
            "@type": "oa:Annotation",
            "motivation": "sc:painting",
            "annotatedBy": {
                "name": "OCR"
            },
            "resource": {
                "@type": "cnt:ContentAsText",
                "format": "text/html",
                "chars": "<span id='b244a4df-430f-463a-b154-cab2a1c9eeae' data-letter-spacing='0.15833333333333333'>10</span>",
                "language": "en"
            },
            "on": {
                "full": "https://readux.io/iiif/v2/tsnhf/canvas/tsnhf_00000036.tif",
                "@type": "oa:SpecificResource",
                "within": {
                    "@id": "https://readux.io/iiif/v2/tsnhf/manifest",
                    "@type": "sc:Manifest"
                },
                "selector": {
                    "@type": "oa:FragmentSelector",
                    "value": "xywh=1509,2366,75,82",
                    "item": {
                        "@type": "oa:FragmentSelector"
                    }
                }
            },
            "stylesheet": {
                "type": "CssStylesheet",
                "value": ".anno-b244a4df-430f-463a-b154-cab2a1c9eeae: { height: 82px; width: 75px; font-size: 51.25px; }"
            }
        },
        {
            "@context": "http://iiif.io/api/presentation/2/context.json",
            "@id": "8de90463-bcfe-47d5-b187-02e258600fa8",
            "@type": "oa:Annotation",
            "motivation": "sc:painting",
            "annotatedBy": {
                "name": "OCR"
            },
            "resource": {
                "@type": "cnt:ContentAsText",
                "format": "text/html",
                "chars": "<span id='8de90463-bcfe-47d5-b187-02e258600fa8' data-letter-spacing='-0.11413043478260869'>\u00b0</span>",
                "language": "en"
            },
            "on": {
                "full": "https://readux.io/iiif/v2/tsnhf/canvas/tsnhf_00000036.tif",
                "@type": "oa:SpecificResource",
                "within": {
                    "@id": "https://readux.io/iiif/v2/tsnhf/manifest",
                    "@type": "sc:Manifest"
                },
                "selector": {
                    "@type": "oa:FragmentSelector",
                    "value": "xywh=1604,2366,23,82",
                    "item": {
                        "@type": "oa:FragmentSelector"
                    }
                }
            },
            "stylesheet": {
                "type": "CssStylesheet",
                "value": ".anno-8de90463-bcfe-47d5-b187-02e258600fa8: { height: 82px; width: 23px; font-size: 51.25px; }"
            }
        },
        {
            "@context": "http://iiif.io/api/presentation/2/context.json",
            "@id": "701f7676-c68e-49a4-b761-26fbfae2a167",
            "@type": "oa:Annotation",
            "motivation": "sc:painting",
            "annotatedBy": {
                "name": "OCR"
            },
            "resource": {
                "@type": "cnt:ContentAsText",
                "format": "text/html",
                "chars": "<span id='701f7676-c68e-49a4-b761-26fbfae2a167' data-letter-spacing='-0.11413043478260869'>/</span>",
                "language": "en"
            },
            "on": {
                "full": "https://readux.io/iiif/v2/tsnhf/canvas/tsnhf_00000036.tif",
                "@type": "oa:SpecificResource",
                "within": {
                    "@id": "https://readux.io/iiif/v2/tsnhf/manifest",
                    "@type": "sc:Manifest"
                },
                "selector": {
                    "@type": "oa:FragmentSelector",
                    "value": "xywh=1646,2366,23,82",
                    "item": {
                        "@type": "oa:FragmentSelector"
                    }
                }
            },
            "stylesheet": {
                "type": "CssStylesheet",
                "value": ".anno-701f7676-c68e-49a4-b761-26fbfae2a167: { height: 82px; width: 23px; font-size: 51.25px; }"
            }
        },
        {
            "@context": "http://iiif.io/api/presentation/2/context.json",
            "@id": "3c026c02-5ff0-4c76-a0f0-f4ebff854647",
            "@type": "oa:Annotation",
            "motivation": "sc:painting",
            "annotatedBy": {
                "name": "OCR"
            },
            "resource": {
                "@type": "cnt:ContentAsText",
                "format": "text/html",
                "chars": "<span id='3c026c02-5ff0-4c76-a0f0-f4ebff854647' data-letter-spacing='0.13468992248062014'>SEC</span>",
                "language": "en"
            },
            "on": {
                "full": "https://readux.io/iiif/v2/tsnhf/canvas/tsnhf_00000036.tif",
                "@type": "oa:SpecificResource",
                "within": {
                    "@id": "https://readux.io/iiif/v2/tsnhf/manifest",
                    "@type": "sc:Manifest"
                },
                "selector": {
                    "@type": "oa:FragmentSelector",
                    "value": "xywh=1678,2366,129,82",
                    "item": {
                        "@type": "oa:FragmentSelector"
                    }
                }
            },
            "stylesheet": {
                "type": "CssStylesheet",
                "value": ".anno-3c026c02-5ff0-4c76-a0f0-f4ebff854647: { height: 82px; width: 129px; font-size: 51.25px; }"
            }
        },
        {
            "@context": "http://iiif.io/api/presentation/2/context.json",
            "@id": "e9acc59e-58e3-4b67-a462-86dbd41b38cc",
            "@type": "oa:Annotation",
            "motivation": "sc:painting",
            "annotatedBy": {
                "name": "OCR"
            },
            "resource": {
                "@type": "cnt:ContentAsText",
                "format": "text/html",
                "chars": "<span id='e9acc59e-58e3-4b67-a462-86dbd41b38cc' data-letter-spacing='0.04670271416454623'>TERMINATE</span>",
                "language": "en"
            },
            "on": {
                "full": "https://readux.io/iiif/v2/tsnhf/canvas/tsnhf_00000036.tif",
                "@type": "oa:SpecificResource",
                "within": {
                    "@id": "https://readux.io/iiif/v2/tsnhf/manifest",
                    "@type": "sc:Manifest"
                },
                "selector": {
                    "@type": "oa:FragmentSelector",
                    "value": "xywh=1510,2452,393,81",
                    "item": {
                        "@type": "oa:FragmentSelector"
                    }
                }
            },
            "stylesheet": {
                "type": "CssStylesheet",
                "value": ".anno-e9acc59e-58e3-4b67-a462-86dbd41b38cc: { height: 81px; width: 393px; font-size: 50.625px; }"
            }
        },
        {
            "@context": "http://iiif.io/api/presentation/2/context.json",
            "@id": "720ecc8e-42f5-4716-bfaf-6ea8a374ad98",
            "@type": "oa:Annotation",
            "motivation": "sc:painting",
            "annotatedBy": {
                "name": "OCR"
            },
            "resource": {
                "@type": "cnt:ContentAsText",
                "format": "text/html",
                "chars": "<span id='720ecc8e-42f5-4716-bfaf-6ea8a374ad98' data-letter-spacing='0.025'>+</span>",
                "language": "en"
            },
            "on": {
                "full": "https://readux.io/iiif/v2/tsnhf/canvas/tsnhf_00000036.tif",
                "@type": "oa:SpecificResource",
                "within": {
                    "@id": "https://readux.io/iiif/v2/tsnhf/manifest",
                    "@type": "sc:Manifest"
                },
                "selector": {
                    "@type": "oa:FragmentSelector",
                    "value": "xywh=2414,2363,25,78",
                    "item": {
                        "@type": "oa:FragmentSelector"
                    }
                }
            },
            "stylesheet": {
                "type": "CssStylesheet",
                "value": ".anno-720ecc8e-42f5-4716-bfaf-6ea8a374ad98: { height: 78px; width: 25px; font-size: 48.75px; }"
            }
        },
        {
            "@context": "http://iiif.io/api/presentation/2/context.json",
            "@id": "ba632b24-f219-4c83-a2c1-1f1ff26f20c8",
            "@type": "oa:Annotation",
            "motivation": "sc:painting",
            "annotatedBy": {
                "name": "OCR"
            },
            "resource": {
                "@type": "cnt:ContentAsText",
                "format": "text/html",
                "chars": "<span id='ba632b24-f219-4c83-a2c1-1f1ff26f20c8' data-letter-spacing='0.17060810810810811'>10</span>",
                "language": "en"
            },
            "on": {
                "full": "https://readux.io/iiif/v2/tsnhf/canvas/tsnhf_00000036.tif",
                "@type": "oa:SpecificResource",
                "within": {
                    "@id": "https://readux.io/iiif/v2/tsnhf/manifest",
                    "@type": "sc:Manifest"
                },
                "selector": {
                    "@type": "oa:FragmentSelector",
                    "value": "xywh=2459,2362,74,78",
                    "item": {
                        "@type": "oa:FragmentSelector"
                    }
                }
            },
            "stylesheet": {
                "type": "CssStylesheet",
                "value": ".anno-ba632b24-f219-4c83-a2c1-1f1ff26f20c8: { height: 78px; width: 74px; font-size: 48.75px; }"
            }
        },
        {
            "@context": "http://iiif.io/api/presentation/2/context.json",
            "@id": "c9cac1aa-8676-4ee7-9180-5aad6b1d5bd0",
            "@type": "oa:Annotation",
            "motivation": "sc:painting",
            "annotatedBy": {
                "name": "OCR"
            },
            "resource": {
                "@type": "cnt:ContentAsText",
                "format": "text/html",
                "chars": "<span id='c9cac1aa-8676-4ee7-9180-5aad6b1d5bd0' data-letter-spacing='0.0125'>\u00b0</span>",
                "language": "en"
            },
            "on": {
                "full": "https://readux.io/iiif/v2/tsnhf/canvas/tsnhf_00000036.tif",
                "@type": "oa:SpecificResource",
                "within": {
                    "@id": "https://readux.io/iiif/v2/tsnhf/manifest",
                    "@type": "sc:Manifest"
                },
                "selector": {
                    "@type": "oa:FragmentSelector",
                    "value": "xywh=2551,2360,25,79",
                    "item": {
                        "@type": "oa:FragmentSelector"
                    }
                }
            },
            "stylesheet": {
                "type": "CssStylesheet",
                "value": ".anno-c9cac1aa-8676-4ee7-9180-5aad6b1d5bd0: { height: 79px; width: 25px; font-size: 49.375px; }"
            }
        },
        {
            "@context": "http://iiif.io/api/presentation/2/context.json",
            "@id": "aeadc42c-00fe-4c59-b2dd-f631273245a3",
            "@type": "oa:Annotation",
            "motivation": "sc:painting",
            "annotatedBy": {
                "name": "OCR"
            },
            "resource": {
                "@type": "cnt:ContentAsText",
                "format": "text/html",
                "chars": "<span id='aeadc42c-00fe-4c59-b2dd-f631273245a3' data-letter-spacing='0.054877177949157384'>TERMINATE</span>",
                "language": "en"
            },
            "on": {
                "full": "https://readux.io/iiif/v2/tsnhf/canvas/tsnhf_00000036.tif",
                "@type": "oa:SpecificResource",
                "within": {
                    "@id": "https://readux.io/iiif/v2/tsnhf/manifest",
                    "@type": "sc:Manifest"
                },
                "selector": {
                    "@type": "oa:FragmentSelector",
                    "value": "xywh=2279,2458,389,70",
                    "item": {
                        "@type": "oa:FragmentSelector"
                    }
                }
            },
            "stylesheet": {
                "type": "CssStylesheet",
                "value": ".anno-aeadc42c-00fe-4c59-b2dd-f631273245a3: { height: 70px; width: 389px; font-size: 43.75px; }"
            }
        },
        {
            "@context": "http://iiif.io/api/presentation/2/context.json",
            "@id": "176f82ac-4529-48e1-a78d-a299521d2ded",
            "@type": "oa:Annotation",
            "motivation": "sc:painting",
            "annotatedBy": {
                "name": "OCR"
            },
            "resource": {
                "@type": "cnt:ContentAsText",
                "format": "text/html",
                "chars": "<span id='176f82ac-4529-48e1-a78d-a299521d2ded' data-letter-spacing='0.25731382978723405'>BT</span>",
                "language": "en"
            },
            "on": {
                "full": "https://readux.io/iiif/v2/tsnhf/canvas/tsnhf_00000036.tif",
                "@type": "oa:SpecificResource",
                "within": {
                    "@id": "https://readux.io/iiif/v2/tsnhf/manifest",
                    "@type": "sc:Manifest"
                },
                "selector": {
                    "@type": "oa:FragmentSelector",
                    "value": "xywh=3144,2411,94,73",
                    "item": {
                        "@type": "oa:FragmentSelector"
                    }
                }
            },
            "stylesheet": {
                "type": "CssStylesheet",
                "value": ".anno-176f82ac-4529-48e1-a78d-a299521d2ded: { height: 73px; width: 94px; font-size: 45.625px; }"
            }
        },
        {
            "@context": "http://iiif.io/api/presentation/2/context.json",
            "@id": "e44fe8fa-5cdf-4e44-86a5-dbd8b3b9bfb1",
            "@type": "oa:Annotation",
            "motivation": "sc:painting",
            "annotatedBy": {
                "name": "OCR"
            },
            "resource": {
                "@type": "cnt:ContentAsText",
                "format": "text/html",
                "chars": "<span id='e44fe8fa-5cdf-4e44-86a5-dbd8b3b9bfb1' data-letter-spacing='-0.08630952380952381'>+</span>",
                "language": "en"
            },
            "on": {
                "full": "https://readux.io/iiif/v2/tsnhf/canvas/tsnhf_00000036.tif",
                "@type": "oa:SpecificResource",
                "within": {
                    "@id": "https://readux.io/iiif/v2/tsnhf/manifest",
                    "@type": "sc:Manifest"
                },
                "selector": {
                    "@type": "oa:FragmentSelector",
                    "value": "xywh=3296,2410,21,73",
                    "item": {
                        "@type": "oa:FragmentSelector"
                    }
                }
            },
            "stylesheet": {
                "type": "CssStylesheet",
                "value": ".anno-e44fe8fa-5cdf-4e44-86a5-dbd8b3b9bfb1: { height: 73px; width: 21px; font-size: 45.625px; }"
            }
        },
        {
            "@context": "http://iiif.io/api/presentation/2/context.json",
            "@id": "fc495a1f-2c98-4598-9558-44326efdbbcd",
            "@type": "oa:Annotation",
            "motivation": "sc:painting",
            "annotatedBy": {
                "name": "OCR"
            },
            "resource": {
                "@type": "cnt:ContentAsText",
                "format": "text/html",
                "chars": "<span id='fc495a1f-2c98-4598-9558-44326efdbbcd' data-letter-spacing='-0.08630952380952381'>1</span>",
                "language": "en"
            },
            "on": {
                "full": "https://readux.io/iiif/v2/tsnhf/canvas/tsnhf_00000036.tif",
                "@type": "oa:SpecificResource",
                "within": {
                    "@id": "https://readux.io/iiif/v2/tsnhf/manifest",
                    "@type": "sc:Manifest"
                },
                "selector": {
                    "@type": "oa:FragmentSelector",
                    "value": "xywh=3392,2410,21,73",
                    "item": {
                        "@type": "oa:FragmentSelector"
                    }
                }
            },
            "stylesheet": {
                "type": "CssStylesheet",
                "value": ".anno-fc495a1f-2c98-4598-9558-44326efdbbcd: { height: 73px; width: 21px; font-size: 45.625px; }"
            }
        },
        {
            "@context": "http://iiif.io/api/presentation/2/context.json",
            "@id": "669f8cd5-1ab8-469d-baa2-3e1d432cfa37",
            "@type": "oa:Annotation",
            "motivation": "sc:painting",
            "annotatedBy": {
                "name": "OCR"
            },
            "resource": {
                "@type": "cnt:ContentAsText",
                "format": "text/html",
                "chars": "<span id='669f8cd5-1ab8-469d-baa2-3e1d432cfa37' data-letter-spacing='0.1572420634920635'>SEC</span>",
                "language": "en"
            },
            "on": {
                "full": "https://readux.io/iiif/v2/tsnhf/canvas/tsnhf_00000036.tif",
                "@type": "oa:SpecificResource",
                "within": {
                    "@id": "https://readux.io/iiif/v2/tsnhf/manifest",
                    "@type": "sc:Manifest"
                },
                "selector": {
                    "@type": "oa:FragmentSelector",
                    "value": "xywh=3467,2410,126,71",
                    "item": {
                        "@type": "oa:FragmentSelector"
                    }
                }
            },
            "stylesheet": {
                "type": "CssStylesheet",
                "value": ".anno-669f8cd5-1ab8-469d-baa2-3e1d432cfa37: { height: 71px; width: 126px; font-size: 44.375px; }"
            }
        },
        {
            "@context": "http://iiif.io/api/presentation/2/context.json",
            "@id": "24c78660-aaee-4b2b-9c3b-51764673ddcd",
            "@type": "oa:Annotation",
            "motivation": "sc:painting",
            "annotatedBy": {
                "name": "OCR"
            },
            "resource": {
                "@type": "cnt:ContentAsText",
                "format": "text/html",
                "chars": "<span id='24c78660-aaee-4b2b-9c3b-51764673ddcd' data-letter-spacing='0.16772151898734178'>IF</span>",
                "language": "en"
            },
            "on": {
                "full": "https://readux.io/iiif/v2/tsnhf/canvas/tsnhf_00000036.tif",
                "@type": "oa:SpecificResource",
                "within": {
                    "@id": "https://readux.io/iiif/v2/tsnhf/manifest",
                    "@type": "sc:Manifest"
                },
                "selector": {
                    "@type": "oa:FragmentSelector",
                    "value": "xywh=3863,2329,79,84",
                    "item": {
                        "@type": "oa:FragmentSelector"
                    }
                }
            },
            "stylesheet": {
                "type": "CssStylesheet",
                "value": ".anno-24c78660-aaee-4b2b-9c3b-51764673ddcd: { height: 84px; width: 79px; font-size: 52.5px; }"
            }
        },
        {
            "@context": "http://iiif.io/api/presentation/2/context.json",
            "@id": "39c9a4bc-2bd6-4971-8405-bcba9cb9f585",
            "@type": "oa:Annotation",
            "motivation": "sc:painting",
            "annotatedBy": {
                "name": "OCR"
            },
            "resource": {
                "@type": "cnt:ContentAsText",
                "format": "text/html",
                "chars": "<span id='39c9a4bc-2bd6-4971-8405-bcba9cb9f585' data-letter-spacing='-0.10677083333333333'><</span>",
                "language": "en"
            },
            "on": {
                "full": "https://readux.io/iiif/v2/tsnhf/canvas/tsnhf_00000036.tif",
                "@type": "oa:SpecificResource",
                "within": {
                    "@id": "https://readux.io/iiif/v2/tsnhf/manifest",
                    "@type": "sc:Manifest"
                },
                "selector": {
                    "@type": "oa:FragmentSelector",
                    "value": "xywh=4006,2328,24,85",
                    "item": {
                        "@type": "oa:FragmentSelector"
                    }
                }
            },
            "stylesheet": {
                "type": "CssStylesheet",
                "value": ".anno-39c9a4bc-2bd6-4971-8405-bcba9cb9f585: { height: 85px; width: 24px; font-size: 53.125px; }"
            }
        },
        {
            "@context": "http://iiif.io/api/presentation/2/context.json",
            "@id": "4237fc6d-003d-4d14-acae-db858adc3c06",
            "@type": "oa:Annotation",
            "motivation": "sc:painting",
            "annotatedBy": {
                "name": "OCR"
            },
            "resource": {
                "@type": "cnt:ContentAsText",
                "format": "text/html",
                "chars": "<span id='4237fc6d-003d-4d14-acae-db858adc3c06' data-letter-spacing='-0.0625'>2</span>",
                "language": "en"
            },
            "on": {
                "full": "https://readux.io/iiif/v2/tsnhf/canvas/tsnhf_00000036.tif",
                "@type": "oa:SpecificResource",
                "within": {
                    "@id": "https://readux.io/iiif/v2/tsnhf/manifest",
                    "@type": "sc:Manifest"
                },
                "selector": {
                    "@type": "oa:FragmentSelector",
                    "value": "xywh=4092,2327,25,85",
                    "item": {
                        "@type": "oa:FragmentSelector"
                    }
                }
            },
            "stylesheet": {
                "type": "CssStylesheet",
                "value": ".anno-4237fc6d-003d-4d14-acae-db858adc3c06: { height: 85px; width: 25px; font-size: 53.125px; }"
            }
        },
        {
            "@context": "http://iiif.io/api/presentation/2/context.json",
            "@id": "0120d2cf-fcb0-483f-89c9-107b759e8ade",
            "@type": "oa:Annotation",
            "motivation": "sc:painting",
            "annotatedBy": {
                "name": "OCR"
            },
            "resource": {
                "@type": "cnt:ContentAsText",
                "format": "text/html",
                "chars": "<span id='0120d2cf-fcb0-483f-89c9-107b759e8ade' data-letter-spacing='0.09895833333333334'>FPS</span>",
                "language": "en"
            },
            "on": {
                "full": "https://readux.io/iiif/v2/tsnhf/canvas/tsnhf_00000036.tif",
                "@type": "oa:SpecificResource",
                "within": {
                    "@id": "https://readux.io/iiif/v2/tsnhf/manifest",
                    "@type": "sc:Manifest"
                },
                "selector": {
                    "@type": "oa:FragmentSelector",
                    "value": "xywh=4184,2326,112,84",
                    "item": {
                        "@type": "oa:FragmentSelector"
                    }
                }
            },
            "stylesheet": {
                "type": "CssStylesheet",
                "value": ".anno-0120d2cf-fcb0-483f-89c9-107b759e8ade: { height: 84px; width: 112px; font-size: 52.5px; }"
            }
        },
        {
            "@context": "http://iiif.io/api/presentation/2/context.json",
            "@id": "40a63e29-ef6a-4b36-acbe-dfb591d47f1f",
            "@type": "oa:Annotation",
            "motivation": "sc:painting",
            "annotatedBy": {
                "name": "OCR"
            },
            "resource": {
                "@type": "cnt:ContentAsText",
                "format": "text/html",
                "chars": "<span id='40a63e29-ef6a-4b36-acbe-dfb591d47f1f' data-letter-spacing='-0.0625'>,</span>",
                "language": "en"
            },
            "on": {
                "full": "https://readux.io/iiif/v2/tsnhf/canvas/tsnhf_00000036.tif",
                "@type": "oa:SpecificResource",
                "within": {
                    "@id": "https://readux.io/iiif/v2/tsnhf/manifest",
                    "@type": "sc:Manifest"
                },
                "selector": {
                    "@type": "oa:FragmentSelector",
                    "value": "xywh=4325,2324,25,85",
                    "item": {
                        "@type": "oa:FragmentSelector"
                    }
                }
            },
            "stylesheet": {
                "type": "CssStylesheet",
                "value": ".anno-40a63e29-ef6a-4b36-acbe-dfb591d47f1f: { height: 85px; width: 25px; font-size: 53.125px; }"
            }
        },
        {
            "@context": "http://iiif.io/api/presentation/2/context.json",
            "@id": "845afb0b-a298-403f-ad89-e72aad3434f1",
            "@type": "oa:Annotation",
            "motivation": "sc:painting",
            "annotatedBy": {
                "name": "OCR"
            },
            "resource": {
                "@type": "cnt:ContentAsText",
                "format": "text/html",
                "chars": "<span id='845afb0b-a298-403f-ad89-e72aad3434f1' data-letter-spacing='0.076158940397351'>TRIM</span>",
                "language": "en"
            },
            "on": {
                "full": "https://readux.io/iiif/v2/tsnhf/canvas/tsnhf_00000036.tif",
                "@type": "oa:SpecificResource",
                "within": {
                    "@id": "https://readux.io/iiif/v2/tsnhf/manifest",
                    "@type": "sc:Manifest"
                },
                "selector": {
                    "@type": "oa:FragmentSelector",
                    "value": "xywh=4409,2324,151,84",
                    "item": {
                        "@type": "oa:FragmentSelector"
                    }
                }
            },
            "stylesheet": {
                "type": "CssStylesheet",
                "value": ".anno-845afb0b-a298-403f-ad89-e72aad3434f1: { height: 84px; width: 151px; font-size: 52.5px; }"
            }
        },
        {
            "@context": "http://iiif.io/api/presentation/2/context.json",
            "@id": "6606da4b-cbd9-4cd9-bf21-a8ea90eba551",
            "@type": "oa:Annotation",
            "motivation": "sc:painting",
            "annotatedBy": {
                "name": "OCR"
            },
            "resource": {
                "@type": "cnt:ContentAsText",
                "format": "text/html",
                "chars": "<span id='6606da4b-cbd9-4cd9-bf21-a8ea90eba551' data-letter-spacing='-0.13095238095238096'>X</span>",
                "language": "en"
            },
            "on": {
                "full": "https://readux.io/iiif/v2/tsnhf/canvas/tsnhf_00000036.tif",
                "@type": "oa:SpecificResource",
                "within": {
                    "@id": "https://readux.io/iiif/v2/tsnhf/manifest",
                    "@type": "sc:Manifest"
                },
                "selector": {
                    "@type": "oa:FragmentSelector",
                    "value": "xywh=3870,2409,21,76",
                    "item": {
                        "@type": "oa:FragmentSelector"
                    }
                }
            },
            "stylesheet": {
                "type": "CssStylesheet",
                "value": ".anno-6606da4b-cbd9-4cd9-bf21-a8ea90eba551: { height: 76px; width: 21px; font-size: 47.5px; }"
            }
        },
        {
            "@context": "http://iiif.io/api/presentation/2/context.json",
            "@id": "ad9a20b6-367b-4cc2-ad03-aa2f9e7f952a",
            "@type": "oa:Annotation",
            "motivation": "sc:painting",
            "annotatedBy": {
                "name": "OCR"
            },
            "resource": {
                "@type": "cnt:ContentAsText",
                "format": "text/html",
                "chars": "<span id='ad9a20b6-367b-4cc2-ad03-aa2f9e7f952a' data-letter-spacing='0.10429447852760736'>AXIS</span>",
                "language": "en"
            },
            "on": {
                "full": "https://readux.io/iiif/v2/tsnhf/canvas/tsnhf_00000036.tif",
                "@type": "oa:SpecificResource",
                "within": {
                    "@id": "https://readux.io/iiif/v2/tsnhf/manifest",
                    "@type": "sc:Manifest"
                },
                "selector": {
                    "@type": "oa:FragmentSelector",
                    "value": "xywh=3956,2409,163,76",
                    "item": {
                        "@type": "oa:FragmentSelector"
                    }
                }
            },
            "stylesheet": {
                "type": "CssStylesheet",
                "value": ".anno-ad9a20b6-367b-4cc2-ad03-aa2f9e7f952a: { height: 76px; width: 163px; font-size: 47.5px; }"
            }
        },
        {
            "@context": "http://iiif.io/api/presentation/2/context.json",
            "@id": "df32f1c8-f339-4964-b5c4-60e40daf8e08",
            "@type": "oa:Annotation",
            "motivation": "sc:painting",
            "annotatedBy": {
                "name": "OCR"
            },
            "resource": {
                "@type": "cnt:ContentAsText",
                "format": "text/html",
                "chars": "<span id='df32f1c8-f339-4964-b5c4-60e40daf8e08' data-letter-spacing='0.08333333333333333'>TO</span>",
                "language": "en"
            },
            "on": {
                "full": "https://readux.io/iiif/v2/tsnhf/canvas/tsnhf_00000036.tif",
                "@type": "oa:SpecificResource",
                "within": {
                    "@id": "https://readux.io/iiif/v2/tsnhf/manifest",
                    "@type": "sc:Manifest"
                },
                "selector": {
                    "@type": "oa:FragmentSelector",
                    "value": "xywh=4190,2409,57,76",
                    "item": {
                        "@type": "oa:FragmentSelector"
                    }
                }
            },
            "stylesheet": {
                "type": "CssStylesheet",
                "value": ".anno-df32f1c8-f339-4964-b5c4-60e40daf8e08: { height: 76px; width: 57px; font-size: 47.5px; }"
            }
        },
        {
            "@context": "http://iiif.io/api/presentation/2/context.json",
            "@id": "15cb4cdc-5aa4-48ac-af59-296b5a7d1371",
            "@type": "oa:Annotation",
            "motivation": "sc:painting",
            "annotatedBy": {
                "name": "OCR"
            },
            "resource": {
                "@type": "cnt:ContentAsText",
                "format": "text/html",
                "chars": "<span id='15cb4cdc-5aa4-48ac-af59-296b5a7d1371' data-letter-spacing='0.15203562340966922'>0.2</span>",
                "language": "en"
            },
            "on": {
                "full": "https://readux.io/iiif/v2/tsnhf/canvas/tsnhf_00000036.tif",
                "@type": "oa:SpecificResource",
                "within": {
                    "@id": "https://readux.io/iiif/v2/tsnhf/manifest",
                    "@type": "sc:Manifest"
                },
                "selector": {
                    "@type": "oa:FragmentSelector",
                    "value": "xywh=4306,2409,131,76",
                    "item": {
                        "@type": "oa:FragmentSelector"
                    }
                }
            },
            "stylesheet": {
                "type": "CssStylesheet",
                "value": ".anno-15cb4cdc-5aa4-48ac-af59-296b5a7d1371: { height: 76px; width: 131px; font-size: 47.5px; }"
            }
        },
        {
            "@context": "http://iiif.io/api/presentation/2/context.json",
            "@id": "8f23deb4-d99e-49b4-b217-44a09f91abef",
            "@type": "oa:Annotation",
            "motivation": "sc:painting",
            "annotatedBy": {
                "name": "OCR"
            },
            "resource": {
                "@type": "cnt:ContentAsText",
                "format": "text/html",
                "chars": "<span id='8f23deb4-d99e-49b4-b217-44a09f91abef' data-letter-spacing='0.13705234159779614'>FPS</span>",
                "language": "en"
            },
            "on": {
                "full": "https://readux.io/iiif/v2/tsnhf/canvas/tsnhf_00000036.tif",
                "@type": "oa:SpecificResource",
                "within": {
                    "@id": "https://readux.io/iiif/v2/tsnhf/manifest",
                    "@type": "sc:Manifest"
                },
                "selector": {
                    "@type": "oa:FragmentSelector",
                    "value": "xywh=4494,2409,121,76",
                    "item": {
                        "@type": "oa:FragmentSelector"
                    }
                }
            },
            "stylesheet": {
                "type": "CssStylesheet",
                "value": ".anno-8f23deb4-d99e-49b4-b217-44a09f91abef: { height: 76px; width: 121px; font-size: 47.5px; }"
            }
        },
        {
            "@context": "http://iiif.io/api/presentation/2/context.json",
            "@id": "5dfb5673-7b99-4ad0-b93d-caad5323b795",
            "@type": "oa:Annotation",
            "motivation": "sc:painting",
            "annotatedBy": {
                "name": "OCR"
            },
            "resource": {
                "@type": "cnt:ContentAsText",
                "format": "text/html",
                "chars": "<span id='5dfb5673-7b99-4ad0-b93d-caad5323b795' data-letter-spacing='0.15871710526315788'>IF</span>",
                "language": "en"
            },
            "on": {
                "full": "https://readux.io/iiif/v2/tsnhf/canvas/tsnhf_00000036.tif",
                "@type": "oa:SpecificResource",
                "within": {
                    "@id": "https://readux.io/iiif/v2/tsnhf/manifest",
                    "@type": "sc:Manifest"
                },
                "selector": {
                    "@type": "oa:FragmentSelector",
                    "value": "xywh=3865,2503,76,83",
                    "item": {
                        "@type": "oa:FragmentSelector"
                    }
                }
            },
            "stylesheet": {
                "type": "CssStylesheet",
                "value": ".anno-5dfb5673-7b99-4ad0-b93d-caad5323b795: { height: 83px; width: 76px; font-size: 51.875px; }"
            }
        },
        {
            "@context": "http://iiif.io/api/presentation/2/context.json",
            "@id": "ebfd1e56-1355-4971-9111-6ff228964106",
            "@type": "oa:Annotation",
            "motivation": "sc:painting",
            "annotatedBy": {
                "name": "OCR"
            },
            "resource": {
                "@type": "cnt:ContentAsText",
                "format": "text/html",
                "chars": "<span id='ebfd1e56-1355-4971-9111-6ff228964106' data-letter-spacing='-0.08072916666666667'>></span>",
                "language": "en"
            },
            "on": {
                "full": "https://readux.io/iiif/v2/tsnhf/canvas/tsnhf_00000036.tif",
                "@type": "oa:SpecificResource",
                "within": {
                    "@id": "https://readux.io/iiif/v2/tsnhf/manifest",
                    "@type": "sc:Manifest"
                },
                "selector": {
                    "@type": "oa:FragmentSelector",
                    "value": "xywh=4004,2503,24,83",
                    "item": {
                        "@type": "oa:FragmentSelector"
                    }
                }
            },
            "stylesheet": {
                "type": "CssStylesheet",
                "value": ".anno-ebfd1e56-1355-4971-9111-6ff228964106: { height: 83px; width: 24px; font-size: 51.875px; }"
            }
        },
        {
            "@context": "http://iiif.io/api/presentation/2/context.json",
            "@id": "c838dfdb-591b-449d-bf6e-4a6551bea1aa",
            "@type": "oa:Annotation",
            "motivation": "sc:painting",
            "annotatedBy": {
                "name": "OCR"
            },
            "resource": {
                "@type": "cnt:ContentAsText",
                "format": "text/html",
                "chars": "<span id='c838dfdb-591b-449d-bf6e-4a6551bea1aa' data-letter-spacing='-0.0375'>2</span>",
                "language": "en"
            },
            "on": {
                "full": "https://readux.io/iiif/v2/tsnhf/canvas/tsnhf_00000036.tif",
                "@type": "oa:SpecificResource",
                "within": {
                    "@id": "https://readux.io/iiif/v2/tsnhf/manifest",
                    "@type": "sc:Manifest"
                },
                "selector": {
                    "@type": "oa:FragmentSelector",
                    "value": "xywh=4096,2503,25,83",
                    "item": {
                        "@type": "oa:FragmentSelector"
                    }
                }
            },
            "stylesheet": {
                "type": "CssStylesheet",
                "value": ".anno-c838dfdb-591b-449d-bf6e-4a6551bea1aa: { height: 83px; width: 25px; font-size: 51.875px; }"
            }
        },
        {
            "@context": "http://iiif.io/api/presentation/2/context.json",
            "@id": "4a55adad-630b-433f-9698-d46969e03f46",
            "@type": "oa:Annotation",
            "motivation": "sc:painting",
            "annotatedBy": {
                "name": "OCR"
            },
            "resource": {
                "@type": "cnt:ContentAsText",
                "format": "text/html",
                "chars": "<span id='4a55adad-630b-433f-9698-d46969e03f46' data-letter-spacing='0.11164529914529915'>FPS</span>",
                "language": "en"
            },
            "on": {
                "full": "https://readux.io/iiif/v2/tsnhf/canvas/tsnhf_00000036.tif",
                "@type": "oa:SpecificResource",
                "within": {
                    "@id": "https://readux.io/iiif/v2/tsnhf/manifest",
                    "@type": "sc:Manifest"
                },
                "selector": {
                    "@type": "oa:FragmentSelector",
                    "value": "xywh=4188,2503,117,83",
                    "item": {
                        "@type": "oa:FragmentSelector"
                    }
                }
            },
            "stylesheet": {
                "type": "CssStylesheet",
                "value": ".anno-4a55adad-630b-433f-9698-d46969e03f46: { height: 83px; width: 117px; font-size: 51.875px; }"
            }
        },
        {
            "@context": "http://iiif.io/api/presentation/2/context.json",
            "@id": "33c1804e-afe6-4245-a10a-749c55e77d41",
            "@type": "oa:Annotation",
            "motivation": "sc:painting",
            "annotatedBy": {
                "name": "OCR"
            },
            "resource": {
                "@type": "cnt:ContentAsText",
                "format": "text/html",
                "chars": "<span id='33c1804e-afe6-4245-a10a-749c55e77d41' data-letter-spacing='-0.08072916666666667'>,</span>",
                "language": "en"
            },
            "on": {
                "full": "https://readux.io/iiif/v2/tsnhf/canvas/tsnhf_00000036.tif",
                "@type": "oa:SpecificResource",
                "within": {
                    "@id": "https://readux.io/iiif/v2/tsnhf/manifest",
                    "@type": "sc:Manifest"
                },
                "selector": {
                    "@type": "oa:FragmentSelector",
                    "value": "xywh=4323,2503,24,83",
                    "item": {
                        "@type": "oa:FragmentSelector"
                    }
                }
            },
            "stylesheet": {
                "type": "CssStylesheet",
                "value": ".anno-33c1804e-afe6-4245-a10a-749c55e77d41: { height: 83px; width: 24px; font-size: 51.875px; }"
            }
        },
        {
            "@context": "http://iiif.io/api/presentation/2/context.json",
            "@id": "e61577b0-7599-4eb3-881f-8abd70ad8855",
            "@type": "oa:Annotation",
            "motivation": "sc:painting",
            "annotatedBy": {
                "name": "OCR"
            },
            "resource": {
                "@type": "cnt:ContentAsText",
                "format": "text/html",
                "chars": "<span id='e61577b0-7599-4eb3-881f-8abd70ad8855' data-letter-spacing='0.15871710526315788'>NO</span>",
                "language": "en"
            },
            "on": {
                "full": "https://readux.io/iiif/v2/tsnhf/canvas/tsnhf_00000036.tif",
                "@type": "oa:SpecificResource",
                "within": {
                    "@id": "https://readux.io/iiif/v2/tsnhf/manifest",
                    "@type": "sc:Manifest"
                },
                "selector": {
                    "@type": "oa:FragmentSelector",
                    "value": "xywh=4402,2503,76,83",
                    "item": {
                        "@type": "oa:FragmentSelector"
                    }
                }
            },
            "stylesheet": {
                "type": "CssStylesheet",
                "value": ".anno-e61577b0-7599-4eb3-881f-8abd70ad8855: { height: 83px; width: 76px; font-size: 51.875px; }"
            }
        },
        {
            "@context": "http://iiif.io/api/presentation/2/context.json",
            "@id": "920a8222-f57c-4304-9e0d-6c71ab4ef430",
            "@type": "oa:Annotation",
            "motivation": "sc:painting",
            "annotatedBy": {
                "name": "OCR"
            },
            "resource": {
                "@type": "cnt:ContentAsText",
                "format": "text/html",
                "chars": "<span id='920a8222-f57c-4304-9e0d-6c71ab4ef430' data-letter-spacing='0.08157467532467533'>TRIM</span>",
                "language": "en"
            },
            "on": {
                "full": "https://readux.io/iiif/v2/tsnhf/canvas/tsnhf_00000036.tif",
                "@type": "oa:SpecificResource",
                "within": {
                    "@id": "https://readux.io/iiif/v2/tsnhf/manifest",
                    "@type": "sc:Manifest"
                },
                "selector": {
                    "@type": "oa:FragmentSelector",
                    "value": "xywh=4549,2503,154,83",
                    "item": {
                        "@type": "oa:FragmentSelector"
                    }
                }
            },
            "stylesheet": {
                "type": "CssStylesheet",
                "value": ".anno-920a8222-f57c-4304-9e0d-6c71ab4ef430: { height: 83px; width: 154px; font-size: 51.875px; }"
            }
        },
        {
            "@context": "http://iiif.io/api/presentation/2/context.json",
            "@id": "6baa9c03-ef83-4429-8612-00fff929e73f",
            "@type": "oa:Annotation",
            "motivation": "sc:painting",
            "annotatedBy": {
                "name": "OCR"
            },
            "resource": {
                "@type": "cnt:ContentAsText",
                "format": "text/html",
                "chars": "<span id='6baa9c03-ef83-4429-8612-00fff929e73f' data-letter-spacing='0.11218944099378882'>3-34</span>",
                "language": "en"
            },
            "on": {
                "full": "https://readux.io/iiif/v2/tsnhf/canvas/tsnhf_00000036.tif",
                "@type": "oa:SpecificResource",
                "within": {
                    "@id": "https://readux.io/iiif/v2/tsnhf/manifest",
                    "@type": "sc:Manifest"
                },
                "selector": {
                    "@type": "oa:FragmentSelector",
                    "value": "xywh=2918,4134,161,71",
                    "item": {
                        "@type": "oa:FragmentSelector"
                    }
                }
            },
            "stylesheet": {
                "type": "CssStylesheet",
                "value": ".anno-6baa9c03-ef83-4429-8612-00fff929e73f: { height: 71px; width: 161px; font-size: 44.375px; }"
            }
        }
    ]
}